{"TCGLjZNYC9tNKubJIHSE":{"admin":{"name":"AyoußMadrid","discrim":"7940","id":"240458124522160128"},"user":{"name":"Fall","discrim":"5744","id":"267635331946250241"},"server":{"name":"Lulu’s Candy Kingdom","id":"413183862022209549","channel":"lounge","channel_id":"413183862445703179"},"reason":" spamming ping"},"b7QmFyuTuEbJ5fge8VAw":{"admin":{"name":"AyoußMadrid","discrim":"7940","id":"240458124522160128"},"user":{"name":"AyoußMadrid","discrim":"7940","id":"240458124522160128"},"server":{"name":"Lulu’s Candy Kingdom","id":"413183862022209549","channel":"lounge","channel_id":"413183862445703179"},"reason":" when are you planning on fixing MY FREAKING BUGS!!"}}